{
  "FileName": "RiversideMini_RoyalRecipe",
  "EntryList": [
    {
      "EntryName": "0000",
      "TextList": [
        {
          "Line": 8,
          "OriginalText": "I\u0027ll listen.",
          "TranslatedText": null
        }
      ]
    },
    {
      "EntryName": "0001",
      "TextList": [
        {
          "Line": 12,
          "OriginalText": "Not now.",
          "TranslatedText": null
        }
      ]
    },
    {
      "EntryName": "0002",
      "TextList": [
        {
          "Line": 16,
          "OriginalText": "Give him fruitcake.",
          "TranslatedText": null
        }
      ]
    },
    {
      "EntryName": "0003",
      "TextList": [
        {
          "Line": 20,
          "OriginalText": "Give him monster cake.",
          "TranslatedText": null
        }
      ]
    },
    {
      "EntryName": "0004",
      "TextList": [
        {
          "Line": 24,
          "OriginalText": "Not right now.",
          "TranslatedText": null
        }
      ]
    },
    {
      "EntryName": "Talk00",
      "NPC": "Gotter",
      "TextList": [
        {
          "Line": 28,
          "OriginalText": "Ah, a customer. Are you traveling alone?\nThis inn gets full marks for beauty, so I\nhighly recommend taking a rest here.",
          "TranslatedText": null
        }
      ]
    },
    {
      "EntryName": "Talk01",
      "NPC": "Gotter",
      "TextList": [
        {
          "Line": 32,
          "OriginalText": "Traveling alone—and in the rain no less?\nThis inn is a thing of beauty, rain or\nshine, so it\u0027s a fine place to take a break.",
          "TranslatedText": null
        }
      ]
    },
    {
      "EntryName": "Talk02",
      "NPC": "Gotter",
      "TextList": [
        {
          "Line": 36,
          "OriginalText": "The river here makes for some lovely\nscenery, and if you head northeast from\nhere, you\u0027ll find the Millennio Sandbar.\nThe scenery there is every bit as lovely\nas the scenery here!\n\nI\u0027m something of a connoisseur of\nbeauty, you see—I simply cannot\nresist a beautiful sight!\n",
          "TranslatedText": null
        },
        {
          "Line": 42,
          "OriginalText": "I try to exude this in all things, not least\nof all my own beautiful appearance.",
          "TranslatedText": null
        }
      ]
    },
    {
      "EntryName": "Talk03",
      "NPC": "Gotter",
      "TextList": [
        {
          "Line": 51,
          "OriginalText": "Speaking of, has anyone ever told you...\nYou have the most beautiful features!",
          "TranslatedText": null
        }
      ]
    },
    {
      "EntryName": "Talk04",
      "NPC": "Gotter",
      "TextList": [
        {
          "Line": 55,
          "OriginalText": "Ahh, I do have many fond memories of\nthis beautiful land... If you have the\ntime, would you indulge me?",
          "TranslatedText": null
        }
      ]
    },
    {
      "EntryName": "Talk_Challenge00",
      "NPC": "Gotter",
      "TextList": [
        {
          "Line": 67,
          "OriginalText": "If you head north through Hyrule Field,\nyou\u0027ll see the castle surrounded by that\nfoul aura.\nIt has long been a den of monsters, but\nin its glory days it was surely a thing of\nwondrous beauty.\nIt was in that very castle in those very\ndays that my ancestor... Hmm, my\ngrandfather\u0027s grandfather, I believe...\nAnyway, he worked as the castle\u0027s\nappointed chef! I couldn\u0027t believe\nit myself!\nOh, how I wonder what sorts of cuisine \nmembers of the royal court enjoyed in\nthose good ol\u0027 days...",
          "TranslatedText": null
        },
        {
          "Line": 73,
          "OriginalText": "\nAs a child, I would often suffer meager\nmeals, all while dreaming of the beautiful\ndishes that might have graced my plate.\nOh, if only things had been different!",
          "TranslatedText": null
        },
        {
          "Line": 79,
          "OriginalText": "\nGourmet spiced meat, seafood curry,\nmushroom risotto, egg pudding...\nOh, my, I think I\u0027m salivating.",
          "TranslatedText": null
        },
        {
          "Line": 85,
          "OriginalText": " And it\u0027s my\npursuit of those childhood dreams that\nexplains the fabulous body you see here!\nThese days, I enjoy my time working at\nthese stables, sharing my tales of beauty\nwith any traveler willing to listen.",
          "TranslatedText": null
        },
        {
          "Line": 91,
          "OriginalText": "\nBut I still wonder what could have been.\nAnyway, excuse me... I seem to have\ncaught myself prattling on.\nBut looking upon your perfectly\nsymmetrical face and discussing meals of\nbeauty has rekindled my desire.\nIf you should happen to set foot inside\nHyrule Castle, could you find it in you to\nkeep an eye out for a cookbook?\nThere must be one lying around\nsomewhere in there! I\u0027m simply dying to\nfinally sample the food of the royal court.",
          "TranslatedText": null
        }
      ]
    },
    {
      "EntryName": "Talk_Challenge01",
      "NPC": "Gotter",
      "TextList": [
        {
          "Line": 95,
          "OriginalText": "A cuisine lovely enough to be favored by\nthe Hyrulean royal family... If the recipe\nstill exists, I\u0027d love to try it!",
          "TranslatedText": null
        }
      ]
    },
    {
      "EntryName": "Talk_Challenge02",
      "NPC": "Gotter",
      "TextList": [
        {
          "Line": 104,
          "OriginalText": "You what?! You really discovered a royal\ncookbook?",
          "TranslatedText": null
        }
      ]
    },
    {
      "EntryName": "Talk_Challenge03",
      "NPC": "Gotter",
      "TextList": [
        {
          "Line": 108,
          "OriginalText": "Could I bother you further to prepare the\ndish for me? I must sample it!",
          "TranslatedText": null
        }
      ]
    },
    {
      "EntryName": "Talk_Challenge04",
      "NPC": "Gotter",
      "TextList": [
        {
          "Line": 120,
          "OriginalText": "Could I bother you further to prepare the\ndish for me? I must sample it!",
          "TranslatedText": null
        }
      ]
    },
    {
      "EntryName": "Talk_Challenge05",
      "NPC": "Gotter",
      "TextList": [
        {
          "Line": 137,
          "OriginalText": "To taunt me with such a delectable and\nbeautiful aroma yet not share...\nSo cruel...",
          "TranslatedText": null
        }
      ]
    },
    {
      "EntryName": "Talk_Challenge06",
      "NPC": "Gotter",
      "TextList": [
        {
          "Line": 141,
          "OriginalText": "This... This is the fruitcake said to be\neaten by the princess of Hyrule...",
          "TranslatedText": null
        }
      ]
    },
    {
      "EntryName": "Talk_Challenge07",
      "NPC": "Gotter",
      "TextList": [
        {
          "Line": 145,
          "OriginalText": "*crunch* *munch...munch*\n*gulp*",
          "TranslatedText": null
        }
      ]
    },
    {
      "EntryName": "Talk_Challenge08",
      "NPC": "Gotter",
      "TextList": [
        {
          "Line": 154,
          "OriginalText": "Simply...",
          "TranslatedText": null
        },
        {
          "Line": 158,
          "OriginalText": "delicious...",
          "TranslatedText": null
        },
        {
          "Line": 162,
          "OriginalText": " How could I possibly\ndescribe this experience?\n\n",
          "TranslatedText": null
        },
        {
          "Line": 168,
          "OriginalText": "A refreshing aroma reminiscent of\ngalloping across these majestic planes\non horseback...\nNo, that undersells the dish\u0027s complexity.\n\n\nIt fills me with that heart-thumping\nintensity that seizes your very soul\nwhen you\u0027re spotted by a Guardian!",
          "TranslatedText": null
        }
      ]
    },
    {
      "EntryName": "Talk_Challenge09",
      "NPC": "Gotter",
      "TextList": [
        {
          "Line": 172,
          "OriginalText": "A truly elegant dish!",
          "TranslatedText": null
        },
        {
          "Line": 178,
          "OriginalText": " I never thought I\nwould taste something quite so thrilling.\n\nI really must thank you for giving me\nsuch a beautiful meal!",
          "TranslatedText": null
        },
        {
          "Line": 184,
          "OriginalText": " Here, take this.\nFor your trouble.",
          "TranslatedText": null
        }
      ]
    },
    {
      "EntryName": "Talk_Challenge10",
      "NPC": "Gotter",
      "TextList": [
        {
          "Line": 188,
          "OriginalText": "This monster cake is said to have been a\nfavorite of the minister of Hyrule.",
          "TranslatedText": null
        }
      ]
    },
    {
      "EntryName": "Talk_Challenge11",
      "NPC": "Gotter",
      "TextList": [
        {
          "Line": 197,
          "OriginalText": "It tastes...beautiful...\nHow can I put it into words?",
          "TranslatedText": null
        },
        {
          "Line": 203,
          "OriginalText": "\n\nIt\u0027s like biting into a Chuchu...\n\n\nNo, no, that would be disgusting and\ndangerous. It stimulates the brain, much\nlike being pummeled by a Hinox!",
          "TranslatedText": null
        }
      ]
    },
    {
      "EntryName": "Talk_No",
      "NPC": "Gotter",
      "TextList": [
        {
          "Line": 212,
          "OriginalText": "Oh, I see...\nVery well. I\u0027ll be here if you change\nyour mind.",
          "TranslatedText": null
        }
      ]
    },
    {
      "EntryName": "Talk_Yes",
      "NPC": "Gotter",
      "TextList": [
        {
          "Line": 221,
          "OriginalText": "Oh, you would?\nEven more beautiful on the inside!\nNow, let\u0027s see...",
          "TranslatedText": null
        }
      ]
    },
    {
      "EntryName": "Talk_near00",
      "NPC": "Gotter",
      "TextList": [
        {
          "Line": 230,
          "OriginalText": "I could go for a bite...",
          "TranslatedText": null
        }
      ]
    },
    {
      "EntryName": "Talk_near01",
      "NPC": "Gotter",
      "TextList": [
        {
          "Line": 234,
          "OriginalText": "Mm, royal cuisine...",
          "TranslatedText": null
        }
      ]
    }
  ],
  "IsCompleted": false
}